signella/__init__.py
signella/cli.py
signella/signella.py
signella-0.3.0.dist-info/licenses/LICENSE
signella-0.3.0.dist-info/METADATA
signella-0.3.0.dist-info/WHEEL
signella-0.3.0.dist-info/entry_points.txt
signella-0.3.0.dist-info/top_level.txt
signella-0.3.0.dist-info/RECORD
